<annotation>
	<folder>images</folder>
	<filename>rb1.jpg</filename>
	<path>C:\NYP\IT107 Deep Learning Network\Assignment\data\images\rb1.jpg</path>
	<source>
		<database>Unknown</database>
	</source>
	<size>
		<width>736</width>
		<height>491</height>
		<depth>3</depth>
	</size>
	<segmented>0</segmented>
	<object>
		<name>roller_blade</name>
		<pose>Unspecified</pose>
		<truncated>0</truncated>
		<difficult>0</difficult>
		<bndbox>
			<xmin>212</xmin>
			<ymin>191</ymin>
			<xmax>559</xmax>
			<ymax>438</ymax>
		</bndbox>
	</object>
</annotation>
